{
    "normal1": {
        "name": "Ordinary Charm",
        "id_no": 0,
        "emote": "normal1charm",
        "desc": "Increases the spawn rate of Normal-type Pok\u00e9mon by 2x.",
        "price": {
            "Normal": 50
        },
        "prereqs": {
            "level": 3
        },
        "effects": {
            "Normal": 2
        }
    },
    "normal2": {
        "name": "Unordinary Charm",
        "id_no": 1,
        "emote": "normal2charm",
        "desc": "Increases the spawn rate of Normal-type Pok\u00e9mon by 4x.",
        "price": {
            "Normal": 200
        },
        "effects": {
            "Normal": 4
        },
        "prereqs": {
            "level": 5,
            "charm": 0
        },
        "replaces": 0
    },
    "normal3": {
        "name": "Extraordinary Charm",
        "id_no": 2,
        "emote": "normal3charm",
        "desc": "Increases the spawn rate of Normal-type Pok\u00e9mon by 6x.",
        "price": {
            "Normal": 500
        },
        "effects": {
            "Normal": 6
        },
        "prereqs": {
            "level": 7,
            "charm": 1
        },
        "replaces": 1
    },
    "fire1": {
        "name": "Sunlit Charm",
        "id_no": 3,
        "emote": "fire1charm",
        "desc": "Increases the spawn rate of Fire-type Pok\u00e9mon by 2x.",
        "price": {
            "Fire": 50
        },
        "prereqs": {
            "level": 3
        },
        "effects": {
            "Fire": 2
        }
    },
    "fire2": {
        "name": "Blazing Charm",
        "id_no": 4,
        "emote": "fire2charm",
        "desc": "Increases the spawn rate of Fire-type Pok\u00e9mon by 4x.",
        "price": {
            "Fire": 200
        },
        "effects": {
            "Fire": 4
        },
        "prereqs": {
            "level": 5,
            "charm": 3
        },
        "replaces": 3
    },
    "fire3": {
        "name": "Infernal Charm",
        "id_no": 5,
        "emote": "fire3charm",
        "desc": "Increases the spawn rate of Fire-type Pok\u00e9mon by 6x.",
        "price": {
            "Fire": 500
        },
        "effects": {
            "Fire": 6
        },
        "prereqs": {
            "level": 7,
            "charm": 4
        },
        "replaces": 4
    },
    "water1": {
        "name": "Misty Charm",
        "id_no": 6,
        "emote": "water1charm",
        "desc": "Increases the spawn rate of Water-type Pok\u00e9mon by 2x.",
        "price": {
            "Water": 50
        },
        "prereqs": {
            "level": 3
        },
        "effects": {
            "Water": 2
        }
    },
    "water2": {
        "name": "Cloudburst Charm",
        "id_no": 7,
        "emote": "water2charm",
        "desc": "Increases the spawn rate of Water-type Pok\u00e9mon by 4x.",
        "price": {
            "Water": 200
        },
        "effects": {
            "Water": 4
        },
        "prereqs": {
            "level": 5,
            "charm": 6
        },
        "replaces": 6
    },
    "water3": {
        "name": "Deluge Charm",
        "id_no": 8,
        "emote": "water3charm",
        "desc": "Increases the spawn rate of Water-type Pok\u00e9mon by 6x.",
        "price": {
            "Water": 500
        },
        "effects": {
            "Water": 6
        },
        "prereqs": {
            "level": 7,
            "charm": 7
        },
        "replaces": 7
    },
    "electric1": {
        "name": "Static Charm",
        "id_no": 9,
        "emote": "electric1charm",
        "desc": "Increases the spawn rate of Electric-type Pok\u00e9mon by 2x.",
        "price": {
            "Electric": 50
        },
        "prereqs": {
            "level": 3
        },
        "effects": {
            "Electric": 2
        }
    },
    "electric2": {
        "name": "Surge Charm",
        "id_no": 10,
        "emote": "electric2charm",
        "desc": "Increases the spawn rate of Electric-type Pok\u00e9mon by 4x.",
        "price": {
            "Electric": 200
        },
        "effects": {
            "Electric": 4
        },
        "prereqs": {
            "level": 5,
            "charm": 9
        },
        "replaces": 9
    },
    "electric3": {
        "name": "Thunderbolt Charm",
        "id_no": 11,
        "emote": "electric3charm",
        "desc": "Increases the spawn rate of Electric-type Pok\u00e9mon by 6x.",
        "price": {
            "Electric": 500
        },
        "effects": {
            "Electric": 6
        },
        "prereqs": {
            "level": 7,
            "charm": 10
        },
        "replaces": 10
    },
    "grass1": {
        "name": "Leafy Charm",
        "id_no": 12,
        "emote": "grass1charm",
        "desc": "Increases the spawn rate of Grass-type Pok\u00e9mon by 2x.",
        "price": {
            "Grass": 50
        },
        "prereqs": {
            "level": 3
        },
        "effects": {
            "Grass": 2
        }
    },
    "grass2": {
        "name": "Arboreal Charm",
        "id_no": 13,
        "emote": "grass2charm",
        "desc": "Increases the spawn rate of Grass-type Pok\u00e9mon by 4x.",
        "price": {
            "Grass": 200
        },
        "effects": {
            "Grass": 4
        },
        "prereqs": {
            "level": 5,
            "charm": 12
        },
        "replaces": 12
    },
    "grass3": {
        "name": "Evergreen Charm",
        "id_no": 14,
        "emote": "grass3charm",
        "desc": "Increases the spawn rate of Grass-type Pok\u00e9mon by 6x.",
        "price": {
            "Grass": 500
        },
        "effects": {
            "Grass": 6
        },
        "prereqs": {
            "level": 7,
            "charm": 13
        },
        "replaces": 13
    },
    "ice1": {
        "name": "Shiver Charm",
        "id_no": 15,
        "emote": "ice1charm",
        "desc": "Increases the spawn rate of Ice-type Pok\u00e9mon by 2x.",
        "price": {
            "Ice": 50
        },
        "prereqs": {
            "level": 3
        },
        "effects": {
            "Ice": 2
        }
    },
    "ice2": {
        "name": "Frost Charm",
        "id_no": 16,
        "emote": "ice2charm",
        "desc": "Increases the spawn rate of Ice-type Pok\u00e9mon by 4x.",
        "price": {
            "Ice": 200
        },
        "effects": {
            "Ice": 4
        },
        "prereqs": {
            "level": 5,
            "charm": 15
        },
        "replaces": 15
    },
    "ice3": {
        "name": "Glacial Charm",
        "id_no": 17,
        "emote": "ice3charm",
        "desc": "Increases the spawn rate of Ice-type Pok\u00e9mon by 6x.",
        "price": {
            "Ice": 500
        },
        "effects": {
            "Ice": 6
        },
        "prereqs": {
            "level": 7,
            "charm": 16
        },
        "replaces": 16
    },
    "fighting1": {
        "name": "Brawny Charm",
        "id_no": 18,
        "emote": "fighting1charm",
        "desc": "Increases the spawn rate of Fighting-type Pok\u00e9mon by 2x.",
        "price": {
            "Fighting": 50
        },
        "prereqs": {
            "level": 3
        },
        "effects": {
            "Fighting": 2
        }
    },
    "fighting2": {
        "name": "Combat Charm",
        "id_no": 19,
        "emote": "fighting2charm",
        "desc": "Increases the spawn rate of Fighting-type Pok\u00e9mon by 4x.",
        "price": {
            "Fighting": 200
        },
        "effects": {
            "Fighting": 4
        },
        "prereqs": {
            "level": 5,
            "charm": 18
        },
        "replaces": 18
    },
    "fighting3": {
        "name": "Martial Charm",
        "id_no": 20,
        "emote": "fighting3charm",
        "desc": "Increases the spawn rate of Fighting-type Pok\u00e9mon by 6x.",
        "price": {
            "Fighting": 500
        },
        "effects": {
            "Fighting": 6
        },
        "prereqs": {
            "level": 7,
            "charm": 19
        },
        "replaces": 19
    },
    "poison1": {
        "name": "Sludge Charm",
        "id_no": 21,
        "emote": "poison1charm",
        "desc": "Increases the spawn rate of Poison-type Pok\u00e9mon by 2x.",
        "price": {
            "Poison": 50
        },
        "prereqs": {
            "level": 3
        },
        "effects": {
            "Poison": 2
        }
    },
    "poison2": {
        "name": "Toxic Charm",
        "id_no": 22,
        "emote": "poison2charm",
        "desc": "Increases the spawn rate of Poison-type Pok\u00e9mon by 4x.",
        "price": {
            "Poison": 200
        },
        "effects": {
            "Poison": 4
        },
        "prereqs": {
            "level": 5,
            "charm": 21
        },
        "replaces": 21
    },
    "poison3": {
        "name": "Venomous Charm",
        "id_no": 23,
        "emote": "poison3charm",
        "desc": "Increases the spawn rate of Poison-type Pok\u00e9mon by 6x.",
        "price": {
            "Poison": 500
        },
        "effects": {
            "Poison": 6
        },
        "prereqs": {
            "level": 7,
            "charm": 22
        },
        "replaces": 22
    },
    "ground1": {
        "name": "Earthy Charm",
        "id_no": 24,
        "emote": "ground1charm",
        "desc": "Increases the spawn rate of Ground-type Pok\u00e9mon by 2x.",
        "price": {
            "Ground": 50
        },
        "prereqs": {
            "level": 3
        },
        "effects": {
            "Ground": 2
        }
    },
    "ground2": {
        "name": "Quake Charm",
        "id_no": 25,
        "emote": "ground2charm",
        "desc": "Increases the spawn rate of Ground-type Pok\u00e9mon by 4x.",
        "price": {
            "Ground": 200
        },
        "effects": {
            "Ground": 4
        },
        "prereqs": {
            "level": 5,
            "charm": 24
        },
        "replaces": 24
    },
    "ground3": {
        "name": "Tectonic Charm",
        "id_no": 26,
        "emote": "ground3charm",
        "desc": "Increases the spawn rate of Ground-type Pok\u00e9mon by 6x.",
        "price": {
            "Ground": 500
        },
        "effects": {
            "Ground": 6
        },
        "prereqs": {
            "level": 7,
            "charm": 25
        },
        "replaces": 25
    },
    "flying1": {
        "name": "Airy Charm",
        "id_no": 27,
        "emote": "flying1charm",
        "desc": "Increases the spawn rate of Flying-type Pok\u00e9mon by 2x.",
        "price": {
            "Flying": 50
        },
        "prereqs": {
            "level": 3
        },
        "effects": {
            "Flying": 2
        }
    },
    "flying2": {
        "name": "Soaring Charm",
        "id_no": 28,
        "emote": "flying2charm",
        "desc": "Increases the spawn rate of Flying-type Pok\u00e9mon by 4x.",
        "price": {
            "Flying": 200
        },
        "effects": {
            "Flying": 4
        },
        "prereqs": {
            "level": 5,
            "charm": 27
        },
        "replaces": 27
    },
    "flying3": {
        "name": "Stratosphere Charm",
        "id_no": 29,
        "emote": "flying3charm",
        "desc": "Increases the spawn rate of Flying-type Pok\u00e9mon by 6x.",
        "price": {
            "Flying": 500
        },
        "effects": {
            "Flying": 6
        },
        "prereqs": {
            "level": 7,
            "charm": 28
        },
        "replaces": 28
    },
    "psychic1": {
        "name": "Mind Charm",
        "id_no": 30,
        "emote": "psychic1charm",
        "desc": "Increases the spawn rate of Psychic-type Pok\u00e9mon by 2x.",
        "price": {
            "Psychic": 50
        },
        "prereqs": {
            "level": 3
        },
        "effects": {
            "Psychic": 2
        }
    },
    "psychic2": {
        "name": "Sensory Charm",
        "id_no": 31,
        "emote": "psychic2charm",
        "desc": "Increases the spawn rate of Psychic-type Pok\u00e9mon by 4x.",
        "price": {
            "Psychic": 200
        },
        "effects": {
            "Psychic": 4
        },
        "prereqs": {
            "level": 5,
            "charm": 30
        },
        "replaces": 30
    },
    "psychic3": {
        "name": "Omniscient Charm",
        "id_no": 32,
        "emote": "psychic3charm",
        "desc": "Increases the spawn rate of Psychic-type Pok\u00e9mon by 6x.",
        "price": {
            "Psychic": 500
        },
        "effects": {
            "Psychic": 6
        },
        "prereqs": {
            "level": 7,
            "charm": 31
        },
        "replaces": 31
    },
    "bug1": {
        "name": "Critter Charm",
        "id_no": 33,
        "emote": "bug1charm",
        "desc": "Increases the spawn rate of Bug-type Pok\u00e9mon by 2x.",
        "price": {
            "Bug": 50
        },
        "prereqs": {
            "level": 3
        },
        "effects": {
            "Bug": 2
        }
    },
    "bug2": {
        "name": "Hive Charm",
        "id_no": 34,
        "emote": "bug2charm",
        "desc": "Increases the spawn rate of Bug-type Pok\u00e9mon by 4x.",
        "price": {
            "Bug": 200
        },
        "effects": {
            "Bug": 4
        },
        "prereqs": {
            "level": 5,
            "charm": 33
        },
        "replaces": 33
    },
    "bug3": {
        "name": "Infested Charm",
        "id_no": 35,
        "emote": "bug3charm",
        "desc": "Increases the spawn rate of Bug-type Pok\u00e9mon by 6x.",
        "price": {
            "Bug": 500
        },
        "effects": {
            "Bug": 6
        },
        "prereqs": {
            "level": 7,
            "charm": 34
        },
        "replaces": 34
    },
    "rock1": {
        "name": "Stony Charm",
        "id_no": 36,
        "emote": "rock1charm",
        "desc": "Increases the spawn rate of Rock-type Pok\u00e9mon by 2x.",
        "price": {
            "Rock": 50
        },
        "prereqs": {
            "level": 3
        },
        "effects": {
            "Rock": 2
        }
    },
    "rock2": {
        "name": "Feldspar Charm",
        "id_no": 37,
        "emote": "rock2charm",
        "desc": "Increases the spawn rate of Rock-type Pok\u00e9mon by 4x.",
        "price": {
            "Rock": 200
        },
        "effects": {
            "Rock": 4
        },
        "prereqs": {
            "level": 5,
            "charm": 36
        },
        "replaces": 36
    },
    "rock3": {
        "name": "Corundum Charm",
        "id_no": 38,
        "emote": "rock3charm",
        "desc": "Increases the spawn rate of Rock-type Pok\u00e9mon by 6x.",
        "price": {
            "Rock": 500
        },
        "effects": {
            "Rock": 6
        },
        "prereqs": {
            "level": 7,
            "charm": 37
        },
        "replaces": 37
    },
    "ghost1": {
        "name": "Eerie Charm",
        "id_no": 39,
        "emote": "ghost1charm",
        "desc": "Increases the spawn rate of Ghost-type Pok\u00e9mon by 2x.",
        "price": {
            "Ghost": 50
        },
        "prereqs": {
            "level": 3
        },
        "effects": {
            "Ghost": 2
        }
    },
    "ghost2": {
        "name": "Spirit Charm",
        "id_no": 40,
        "emote": "ghost2charm",
        "desc": "Increases the spawn rate of Ghost-type Pok\u00e9mon by 4x.",
        "price": {
            "Ghost": 200
        },
        "effects": {
            "Ghost": 4
        },
        "prereqs": {
            "level": 5,
            "charm": 39
        },
        "replaces": 39
    },
    "ghost3": {
        "name": "Poltergeist Charm",
        "id_no": 41,
        "emote": "ghost3charm",
        "desc": "Increases the spawn rate of Ghost-type Pok\u00e9mon by 6x.",
        "price": {
            "Ghost": 500
        },
        "effects": {
            "Ghost": 6
        },
        "prereqs": {
            "level": 7,
            "charm": 40
        },
        "replaces": 40
    },
    "dragon1": {
        "name": "Scaly Charm",
        "id_no": 42,
        "emote": "dragon1charm",
        "desc": "Increases the spawn rate of Dragon-type Pok\u00e9mon by 2x.",
        "price": {
            "Dragon": 50
        },
        "prereqs": {
            "level": 3
        },
        "effects": {
            "Dragon": 2
        }
    },
    "dragon2": {
        "name": "Serpentine Charm",
        "id_no": 43,
        "emote": "dragon2charm",
        "desc": "Increases the spawn rate of Dragon-type Pok\u00e9mon by 4x.",
        "price": {
            "Dragon": 200
        },
        "effects": {
            "Dragon": 4
        },
        "prereqs": {
            "level": 5,
            "charm": 42
        },
        "replaces": 42
    },
    "dragon3": {
        "name": "Hydra Charm",
        "id_no": 44,
        "emote": "dragon3charm",
        "desc": "Increases the spawn rate of Dragon-type Pok\u00e9mon by 6x.",
        "price": {
            "Dragon": 500
        },
        "effects": {
            "Dragon": 6
        },
        "prereqs": {
            "level": 7,
            "charm": 43
        },
        "replaces": 43
    },
    "dark1": {
        "name": "Sneaky Charm",
        "id_no": 45,
        "emote": "dark1charm",
        "desc": "Increases the spawn rate of Dark-type Pok\u00e9mon by 2x.",
        "price": {
            "Dark": 50
        },
        "prereqs": {
            "level": 3
        },
        "effects": {
            "Dark": 2
        }
    },
    "dark2": {
        "name": "Mischievous Charm",
        "id_no": 46,
        "emote": "dark2charm",
        "desc": "Increases the spawn rate of Dark-type Pok\u00e9mon by 4x.",
        "price": {
            "Dark": 200
        },
        "effects": {
            "Dark": 4
        },
        "prereqs": {
            "level": 5,
            "charm": 45
        },
        "replaces": 45
    },
    "dark3": {
        "name": "Sinister Charm",
        "id_no": 47,
        "emote": "dark3charm",
        "desc": "Increases the spawn rate of Dark-type Pok\u00e9mon by 6x.",
        "price": {
            "Dark": 500
        },
        "effects": {
            "Dark": 6
        },
        "prereqs": {
            "level": 7,
            "charm": 46
        },
        "replaces": 46
    },
    "steel1": {
        "name": "Forged Charm",
        "id_no": 48,
        "emote": "steel1charm",
        "desc": "Increases the spawn rate of Steel-type Pok\u00e9mon by 2x.",
        "price": {
            "Steel": 50
        },
        "prereqs": {
            "level": 3
        },
        "effects": {
            "Steel": 2
        }
    },
    "steel2": {
        "name": "Reinforced Charm",
        "id_no": 49,
        "emote": "steel2charm",
        "desc": "Increases the spawn rate of Steel-type Pok\u00e9mon by 4x.",
        "price": {
            "Steel": 200
        },
        "effects": {
            "Steel": 4
        },
        "prereqs": {
            "level": 5,
            "charm": 48
        },
        "replaces": 48
    },
    "steel3": {
        "name": "Armored Charm",
        "id_no": 50,
        "emote": "steel3charm",
        "desc": "Increases the spawn rate of Steel-type Pok\u00e9mon by 6x.",
        "price": {
            "Steel": 500
        },
        "effects": {
            "Steel": 6
        },
        "prereqs": {
            "level": 7,
            "charm": 49
        },
        "replaces": 49
    },
    "fairy1": {
        "name": "Pixie Charm",
        "id_no": 51,
        "emote": "fairy1charm",
        "desc": "Increases the spawn rate of Fairy-type Pok\u00e9mon by 2x.",
        "price": {
            "Fairy": 50
        },
        "prereqs": {
            "level": 3
        },
        "effects": {
            "Fairy": 2
        }
    },
    "fairy2": {
        "name": "Mystical Charm",
        "id_no": 52,
        "emote": "fairy2charm",
        "desc": "Increases the spawn rate of Fairy-type Pok\u00e9mon by 4x.",
        "price": {
            "Fairy": 200
        },
        "effects": {
            "Fairy": 4
        },
        "prereqs": {
            "level": 5,
            "charm": 51
        },
        "replaces": 51
    },
    "fairy3": {
        "name": "Ethereal Charm",
        "id_no": 53,
        "emote": "fairy3charm",
        "desc": "Increases the spawn rate of Fairy-type Pok\u00e9mon by 6x.",
        "price": {
            "Fairy": 500
        },
        "effects": {
            "Fairy": 6
        },
        "prereqs": {
            "level": 7,
            "charm": 52
        },
        "replaces": 52
    },
    "candy1": {
        "name": "Candied Charm I",
        "id_no": 54,
        "emote": "candy1charm",
        "desc": "Doubles the token reward for catching a Pok\u00e9mon.",
        "price": {
            "Normal": 50
        },
        "effects": {
            "tokens": 2
        },
        "prereqs": {
            "level": 4
        }
    },
    "candy2": {
        "name": "Candied Charm II",
        "id_no": 55,
        "emote": "candy2charm",
        "desc": "Triples the token reward for catching a Pok\u00e9mon.",
        "price": {
            "Normal": 200
        },
        "effects": {
            "tokens": 3
        },
        "prereqs": {
            "level": 6,
            "charm": 54
        },
        "replaces": 54
    },
    "candy3": {
        "name": "Candied Charm III",
        "id_no": 56,
        "emote": "candy3charm",
        "desc": "Quadruples the token reward for catching a Pok\u00e9mon.",
        "price": {
            "Normal": 500
        },
        "effects": {
            "tokens": 4
        },
        "prereqs": {
            "level": 8,
            "charm": 55
        },
        "replaces": 55
    },
    "capture": {
        "name": "Capture Charm",
        "id_no": 57,
        "emote": "capturecharm",
        "desc": "Increases the catch rate of wild Pok\u00e9mon.",
        "price": {
            "Bug": 150,
            "Steel": 150
        },
        "effects": {
            "catch": 0.2
        },
        "prereqs": {
            "level": 6
        }
    },
    "starter": {
        "name": "Oaken Charm",
        "id_no": 58,
        "emote": "startercharm",
        "desc": "Increases the spawn rate of starter Pok\u00e9mon by 10x.",
        "price": {
            "Grass": 200,
            "Fire": 200,
            "Water": 200
        },
        "effects": {
            "starter": 10
        },
        "prereqs": {
            "level": 8
        }
    },
    "rarity": {
        "name": "Rarity Charm",
        "id_no": 59,
        "emote": "raritycharm",
        "desc": "Increases the spawn rate of rare and uncommon wild Pok\u00e9mon.",
        "price": {
            "Dragon": 250,
            "Fairy": 250
        },
        "effects": {
            "rarity": 1
        },
        "prereqs": {
            "level": 9
        }
    },
    "shiny": {
        "name": "Shiny Charm",
        "id_no": 60,
        "emote": "shinycharm",
        "desc": "Triples the chance of encountering shiny Pok\u00e9mon.",
        "price": {
            "Normal": 1
        },
        "effects": {
            "shiny": 1
        },
        "prereqs": {
            "level": 99
        }
    }
}